alaya_vis_sdk/__init__.py
alaya_vis_sdk/client.py
alaya_vis_sdk/decorators.py
alaya_vis_sdk/types.py
alaya_vis_sdk-0.1.0.dist-info/METADATA
alaya_vis_sdk-0.1.0.dist-info/WHEEL
alaya_vis_sdk-0.1.0.dist-info/top_level.txt
alaya_vis_sdk-0.1.0.dist-info/RECORD
