Metadata-Version: 2.4
Name: alaya-vis-sdk
Version: 0.1.0
Summary: Alaya Visual Trace SDK
Author: AlayaDB-AI
Requires-Python: >=3.8
Requires-Dist: requests>=2.28.0
Requires-Dist: psutil>=5.9.0
